j2static/__init__.py
j2static/build.py
j2static/cli.py
j2static/cli_merge.py
j2static/main.py
j2static/webserver.py
j2static/tools/marks.py
j2static/tools/merge.py
j2static-0.2.3.dist-info/METADATA
j2static-0.2.3.dist-info/RECORD
j2static-0.2.3.dist-info/WHEEL
j2static-0.2.3.dist-info/entry_points.txt
j2static-0.2.3.dist-info/top_level.txt
