Metadata-Version: 2.1
Name: j2static
Version: 0.2.3
Summary: static templating engine
Home-page: https://www.fossgalaxy.com
Author: FOSS Galaxy
Author-email: software@fossgalaxy.com
License: UNKNOWN
Platform: UNKNOWN
Classifier: Development Status :: 3 - Alpha
Classifier: Programming Language :: Python :: 3
Requires-Dist: jinja2
